LICENSE.txt
MANIFEST.in
README.rst
requirements.txt
requirements_for_tests.txt
setup.py
performanceplatform/__init__.py
performanceplatform/collector/__init__.py
performanceplatform/collector/arguments.py
performanceplatform/collector/crontab.py
performanceplatform/collector/logging_setup.py
performanceplatform/collector/main.py
performanceplatform/collector/ga/__init__.py
performanceplatform/collector/ga/core.py
performanceplatform/collector/ga/realtime.py
performanceplatform/collector/ga/trending.py
performanceplatform/collector/ga/contrib/__init__.py
performanceplatform/collector/ga/contrib/content/__init__.py
performanceplatform/collector/ga/contrib/content/table.py
performanceplatform/collector/ga/lib/__init__.py
performanceplatform/collector/ga/lib/helper.py
performanceplatform/collector/ga/plugins/__init__.py
performanceplatform/collector/ga/plugins/aggregate.py
performanceplatform/collector/ga/plugins/comment.py
performanceplatform/collector/ga/plugins/compute_id.py
performanceplatform/collector/ga/plugins/department.py
performanceplatform/collector/ga/plugins/load_plugin.py
performanceplatform/collector/ga/plugins/rank.py
performanceplatform/collector/ga/plugins/remove_key.py
performanceplatform/collector/gcloud/__init__.py
performanceplatform/collector/gcloud/aggregate.py
performanceplatform/collector/gcloud/core.py
performanceplatform/collector/gcloud/sales_parser.py
performanceplatform/collector/gcloud/table_names.py
performanceplatform/collector/gcloud/tests.py
performanceplatform/collector/pingdom/__init__.py
performanceplatform/collector/pingdom/core.py
performanceplatform/collector/piwik/__init__.py
performanceplatform/collector/piwik/base.py
performanceplatform/collector/piwik/core.py
performanceplatform/collector/piwik/realtime.py
performanceplatform/collector/webtrends/__init__.py
performanceplatform/collector/webtrends/base.py
performanceplatform/collector/webtrends/keymetrics.py
performanceplatform/collector/webtrends/reports.py
performanceplatform_collector.egg-info/PKG-INFO
performanceplatform_collector.egg-info/SOURCES.txt
performanceplatform_collector.egg-info/dependency_links.txt
performanceplatform_collector.egg-info/entry_points.txt
performanceplatform_collector.egg-info/namespace_packages.txt
performanceplatform_collector.egg-info/requires.txt
performanceplatform_collector.egg-info/top_level.txt