Metadata-Version: 1.0
Name: performanceplatform-collector
Version: 0.3.0
Summary: performanceplatform-collector: tools for sending data to the Performance Platform
Home-page: https://github.com/alphagov/performanceplatform-collector
Author: Government Digital Service
Author-email: performance@digital.cabinet-office.gov.uk
License: MIT
Keywords: api data performance_platform
Platform: UNKNOWN
